{
  "image": "1923.png",
  "width": 1000,
  "height": 1000,
  "categories": [
    {
      "id": 0,
      "name": "Rubble/excavated earth and rocks"
    },
    {
      "id": 1,
      "name": "Bulky items"
    },
    {
      "id": 2,
      "name": "Fire Wood"
    },
    {
      "id": 3,
      "name": "Scrap"
    },
    {
      "id": 4,
      "name": "Plastic"
    },
    {
      "id": 5,
      "name": "Vehicles"
    },
    {
      "id": 6,
      "name": "Tires"
    },
    {
      "id": 7,
      "name": "Domestic appliances"
    },
    {
      "id": 8,
      "name": "Paper"
    },
    {
      "id": 9,
      "name": "Sludge-Zootechnical waste-Manure"
    },
    {
      "id": 10,
      "name": "Foundry waste"
    },
    {
      "id": 11,
      "name": "Stone/marble processing waste"
    },
    {
      "id": 12,
      "name": "Asphalt milling"
    },
    {
      "id": 13,
      "name": "Corrugated sheets (presumed asbestos-cement)"
    },
    {
      "id": 14,
      "name": "Glass"
    },
    {
      "id": 15,
      "name": "Heaps not delimited"
    },
    {
      "id": 16,
      "name": "Full container"
    },
    {
      "id": 17,
      "name": "Big bags"
    },
    {
      "id": 18,
      "name": "Full pallets"
    },
    {
      "id": 19,
      "name": "Delimited heaps (by barriers/walls/etc)"
    },
    {
      "id": 20,
      "name": "Cisterns"
    },
    {
      "id": 21,
      "name": "Drums bins"
    }
  ],
  "annotations": [
    {
      "id": 0,
      "category_id": 16,
      "class": "Full container",
      "score": 0.8943984508514404,
      "box": [
        193.3497772216797,
        364.0158386230469,
        285.07513427734375,
        551.2250366210938
      ],
      "segmentation": [
        [
          207.8125,
          365.625,
          207.8125,
          370.3125,
          204.6875,
          373.4375,
          203.125,
          373.4375,
          200.0,
          376.5625,
          198.4375,
          376.5625,
          195.3125,
          379.6875,
          190.625,
          379.6875,
          190.625,
          409.375,
          195.3125,
          409.375,
          198.4375,
          412.5,
          198.4375,
          417.1875,
          200.0,
          418.75,
          200.0,
          421.875,
          201.5625,
          423.4375,
          201.5625,
          428.125,
          203.125,
          429.6875,
          203.125,
          432.8125,
          204.6875,
          434.375,
          204.6875,
          437.5,
          206.25,
          439.0625,
          206.25,
          443.75,
          207.8125,
          445.3125,
          207.8125,
          450.0,
          209.375,
          451.5625,
          209.375,
          457.8125,
          210.9375,
          459.375,
          210.9375,
          464.0625,
          212.5,
          465.625,
          212.5,
          468.75,
          214.0625,
          470.3125,
          214.0625,
          473.4375,
          215.625,
          475.0,
          215.625,
          479.6875,
          217.1875,
          481.25,
          217.1875,
          487.5,
          218.75,
          489.0625,
          218.75,
          495.3125,
          220.3125,
          496.875,
          220.3125,
          506.25,
          221.875,
          507.8125,
          221.875,
          520.3125,
          223.4375,
          521.875,
          223.4375,
          531.25,
          225.0,
          532.8125,
          225.0,
          537.5,
          226.5625,
          539.0625,
          226.5625,
          540.625,
          228.125,
          542.1875,
          228.125,
          545.3125,
          231.25,
          548.4375,
          232.8125,
          548.4375,
          234.375,
          550.0,
          240.625,
          550.0,
          242.1875,
          548.4375,
          245.3125,
          548.4375,
          248.4375,
          545.3125,
          250.0,
          545.3125,
          259.375,
          535.9375,
          260.9375,
          535.9375,
          265.625,
          531.25,
          267.1875,
          531.25,
          271.875,
          526.5625,
          273.4375,
          526.5625,
          275.0,
          525.0,
          276.5625,
          525.0,
          278.125,
          523.4375,
          279.6875,
          523.4375,
          281.25,
          521.875,
          281.25,
          520.3125,
          282.8125,
          518.75,
          289.0625,
          518.75,
          289.0625,
          496.875,
          284.375,
          496.875,
          281.25,
          493.75,
          281.25,
          492.1875,
          279.6875,
          490.625,
          279.6875,
          487.5,
          278.125,
          485.9375,
          278.125,
          479.6875,
          276.5625,
          478.125,
          276.5625,
          470.3125,
          275.0,
          468.75,
          275.0,
          459.375,
          273.4375,
          457.8125,
          273.4375,
          450.0,
          271.875,
          448.4375,
          271.875,
          437.5,
          270.3125,
          435.9375,
          270.3125,
          431.25,
          268.75,
          429.6875,
          268.75,
          423.4375,
          267.1875,
          421.875,
          267.1875,
          414.0625,
          265.625,
          412.5,
          265.625,
          409.375,
          264.0625,
          407.8125,
          264.0625,
          401.5625,
          262.5,
          400.0,
          262.5,
          396.875,
          260.9375,
          395.3125,
          260.9375,
          390.625,
          259.375,
          389.0625,
          259.375,
          384.375,
          257.8125,
          382.8125,
          257.8125,
          378.125,
          256.25,
          376.5625,
          256.25,
          373.4375,
          254.6875,
          371.875,
          254.6875,
          365.625
        ]
      ],
      "area": 17171.83053047536,
      "location": {
        "lat": 457.6204376220703,
        "lng": 239.21245574951172
      }
    },
    {
      "id": 1,
      "category_id": 16,
      "class": "Full container",
      "score": 0.8802168965339661,
      "box": [
        357.1495666503906,
        521.9137573242188,
        422.61492919921875,
        555.4800415039062
      ],
      "segmentation": [
        [
          359.375,
          521.875,
          359.375,
          546.875,
          364.0625,
          546.875,
          367.1875,
          550.0,
          368.75,
          550.0,
          370.3125,
          551.5625,
          371.875,
          551.5625,
          373.4375,
          553.125,
          373.4375,
          557.8125,
          412.5,
          557.8125,
          412.5,
          553.125,
          418.75,
          546.875,
          418.75,
          543.75,
          421.875,
          540.625,
          426.5625,
          540.625,
          426.5625,
          535.9375,
          421.875,
          535.9375,
          415.625,
          529.6875,
          414.0625,
          529.6875,
          412.5,
          528.125,
          410.9375,
          528.125,
          409.375,
          526.5625,
          409.375,
          521.875
        ]
      ],
      "area": 2197.428963240236,
      "location": {
        "lat": 538.6968994140625,
        "lng": 389.8822479248047
      }
    },
    {
      "id": 2,
      "category_id": 16,
      "class": "Full container",
      "score": 0.8444362878799438,
      "box": [
        430.1502380371094,
        517.2860107421875,
        489.5725402832031,
        551.1981201171875
      ],
      "segmentation": [
        [
          428.125,
          515.625,
          428.125,
          539.0625,
          434.375,
          539.0625,
          437.5,
          542.1875,
          439.0625,
          542.1875,
          442.1875,
          545.3125,
          443.75,
          545.3125,
          446.875,
          548.4375,
          454.6875,
          548.4375,
          456.25,
          546.875,
          457.8125,
          546.875,
          459.375,
          545.3125,
          476.5625,
          545.3125,
          478.125,
          543.75,
          479.6875,
          543.75,
          485.9375,
          537.5,
          485.9375,
          535.9375,
          487.5,
          534.375,
          487.5,
          532.8125,
          481.25,
          526.5625,
          479.6875,
          526.5625,
          476.5625,
          523.4375,
          473.4375,
          523.4375,
          471.875,
          521.875,
          468.75,
          521.875,
          467.1875,
          520.3125,
          467.1875,
          515.625,
          462.5,
          515.625,
          462.5,
          520.3125,
          460.9375,
          521.875,
          454.6875,
          521.875,
          453.125,
          523.4375,
          451.5625,
          521.875,
          448.4375,
          521.875,
          446.875,
          520.3125,
          446.875,
          515.625
        ]
      ],
      "area": 2015.1356130838394,
      "location": {
        "lat": 534.2420654296875,
        "lng": 459.86138916015625
      }
    },
    {
      "id": 3,
      "category_id": 16,
      "class": "Full container",
      "score": 0.8054897785186768,
      "box": [
        267.6500549316406,
        532.078369140625,
        302.7512512207031,
        558.6532592773438
      ],
      "segmentation": [
        [
          271.875,
          534.375,
          271.875,
          539.0625,
          270.3125,
          540.625,
          265.625,
          540.625,
          265.625,
          554.6875,
          271.875,
          554.6875,
          273.4375,
          556.25,
          282.8125,
          556.25,
          284.375,
          554.6875,
          285.9375,
          554.6875,
          287.5,
          553.125,
          289.0625,
          553.125,
          290.625,
          551.5625,
          293.75,
          551.5625,
          295.3125,
          550.0,
          296.875,
          550.0,
          298.4375,
          548.4375,
          300.0,
          548.4375,
          303.125,
          545.3125,
          307.8125,
          545.3125,
          303.125,
          545.3125,
          301.5625,
          543.75,
          301.5625,
          542.1875,
          300.0,
          540.625,
          300.0,
          534.375
        ]
      ],
      "area": 932.8104350492358,
      "location": {
        "lat": 545.3658142089844,
        "lng": 285.2006530761719
      }
    },
    {
      "id": 4,
      "category_id": 16,
      "class": "Full container",
      "score": 0.7989758253097534,
      "box": [
        405.6214294433594,
        457.86029052734375,
        488.1224670410156,
        498.610595703125
      ],
      "segmentation": [
        [
          426.5625,
          459.375,
          426.5625,
          464.0625,
          423.4375,
          467.1875,
          418.75,
          467.1875,
          417.1875,
          468.75,
          414.0625,
          468.75,
          412.5,
          470.3125,
          403.125,
          470.3125,
          403.125,
          501.5625,
          453.125,
          501.5625,
          453.125,
          496.875,
          454.6875,
          495.3125,
          456.25,
          495.3125,
          457.8125,
          493.75,
          465.625,
          493.75,
          467.1875,
          492.1875,
          473.4375,
          492.1875,
          475.0,
          490.625,
          481.25,
          490.625,
          484.375,
          487.5,
          484.375,
          485.9375,
          485.9375,
          484.375,
          485.9375,
          479.6875,
          487.5,
          478.125,
          485.9375,
          476.5625,
          485.9375,
          467.1875,
          484.375,
          465.625,
          484.375,
          459.375
        ]
      ],
      "area": 3361.942459423095,
      "location": {
        "lat": 478.2354431152344,
        "lng": 446.8719482421875
      }
    },
    {
      "id": 5,
      "category_id": 16,
      "class": "Full container",
      "score": 0.7701623439788818,
      "box": [
        598.2589111328125,
        419.271484375,
        679.9569091796875,
        465.0621643066406
      ],
      "segmentation": [
        [
          623.4375,
          421.875,
          623.4375,
          426.5625,
          620.3125,
          429.6875,
          617.1875,
          429.6875,
          615.625,
          431.25,
          604.6875,
          431.25,
          603.125,
          432.8125,
          596.875,
          432.8125,
          596.875,
          470.3125,
          612.5,
          470.3125,
          612.5,
          465.625,
          614.0625,
          464.0625,
          615.625,
          464.0625,
          617.1875,
          462.5,
          621.875,
          462.5,
          623.4375,
          460.9375,
          628.125,
          460.9375,
          629.6875,
          459.375,
          634.375,
          459.375,
          635.9375,
          457.8125,
          640.625,
          457.8125,
          642.1875,
          456.25,
          643.75,
          456.25,
          645.3125,
          454.6875,
          648.4375,
          454.6875,
          650.0,
          453.125,
          653.125,
          453.125,
          654.6875,
          451.5625,
          656.25,
          451.5625,
          659.375,
          448.4375,
          660.9375,
          448.4375,
          662.5,
          446.875,
          664.0625,
          446.875,
          671.875,
          439.0625,
          671.875,
          437.5,
          673.4375,
          435.9375,
          673.4375,
          432.8125,
          675.0,
          431.25,
          675.0,
          429.6875,
          676.5625,
          428.125,
          676.5625,
          421.875
        ]
      ],
      "area": 3741.006879620254,
      "location": {
        "lat": 442.1668243408203,
        "lng": 639.10791015625
      }
    }
  ],
  "scaling_factor": 1.0
}